LICENSE
MANIFEST.in
README.md
setup.py
docs/About.rst
docs/Changelog.rst
src/senaite/__init__.py
src/senaite.databox.egg-info/PKG-INFO
src/senaite.databox.egg-info/SOURCES.txt
src/senaite.databox.egg-info/dependency_links.txt
src/senaite.databox.egg-info/entry_points.txt
src/senaite.databox.egg-info/namespace_packages.txt
src/senaite.databox.egg-info/not-zip-safe
src/senaite.databox.egg-info/requires.txt
src/senaite.databox.egg-info/top_level.txt
src/senaite/databox/__init__.py
src/senaite/databox/config.py
src/senaite/databox/configure.zcml
src/senaite/databox/converters.py
src/senaite/databox/interfaces.py
src/senaite/databox/permissions.py
src/senaite/databox/permissions.zcml
src/senaite/databox/setuphandlers.py
src/senaite/databox/vocabularies.py
src/senaite/databox/behaviors/__init__.py
src/senaite/databox/behaviors/configure.zcml
src/senaite/databox/behaviors/databox.py
src/senaite/databox/browser/__init__.py
src/senaite/databox/browser/add.py
src/senaite/databox/browser/configure.zcml
src/senaite/databox/browser/edit.py
src/senaite/databox/browser/folder_view.py
src/senaite/databox/browser/form.py
src/senaite/databox/browser/view.py
src/senaite/databox/browser/static/resources.pt
src/senaite/databox/browser/static/assets/icons/databox.svg
src/senaite/databox/browser/static/assets/icons/databoxfolder.svg
src/senaite/databox/browser/static/assets/icons/export_to_csv.svg
src/senaite/databox/browser/static/assets/icons/export_to_excel.svg
src/senaite/databox/browser/static/bundles/senaite.databox.css
src/senaite/databox/browser/static/bundles/senaite.databox.js
src/senaite/databox/browser/templates/databox_controls.pt
src/senaite/databox/browser/templates/databox_edit.pt
src/senaite/databox/browser/templates/databox_view.pt
src/senaite/databox/browser/theme/__init__.py
src/senaite/databox/browser/theme/configure.zcml
src/senaite/databox/browser/theme/icons.py
src/senaite/databox/browser/viewlets/__init__.py
src/senaite/databox/browser/viewlets/configure.zcml
src/senaite/databox/content/__init__.py
src/senaite/databox/content/databox.py
src/senaite/databox/content/databoxfolder.py
src/senaite/databox/locales/senaite.databox-manual.pot
src/senaite/databox/locales/senaite.databox.pot
src/senaite/databox/locales/.tx/config
src/senaite/databox/locales/cs/LC_MESSAGES/senaite.databox.mo
