Metadata-Version: 2.1
Name: senaite.databox
Version: 1.5.0
Summary: A configurable data exporter
Home-page: https://github.com/senaite/senaite.databox
Author: RIDING BYTES & NARALABS
Author-email: senaite@senaite.com
License: GPLv2
Platform: UNKNOWN
Classifier: Framework :: Plone
Classifier: Framework :: Zope2
Classifier: Programming Language :: Python
Classifier: Development Status :: 5 - Production/Stable
Classifier: License :: OSI Approved :: GNU General Public License v2 (GPLv2)
Provides-Extra: test
